LICENSE
README.md
fastzipfile.py
setup.py
extension/_zipdecryptermodule.c
fastzipfile.egg-info/PKG-INFO
fastzipfile.egg-info/SOURCES.txt
fastzipfile.egg-info/dependency_links.txt
fastzipfile.egg-info/not-zip-safe
fastzipfile.egg-info/top_level.txt
tests/test_fastzipfile.py