Metadata-Version: 2.1
Name: fastzipfile
Version: 2.3.1
Summary: Read password protected Zips 100x faster
Home-page: https://github.com/kamilmahmood/fastzipfile
Author: Kamil Mahmood
Author-email: kamil.mahmood@outlook.com
Keywords: zip zipfile fastzip
Classifier: Development Status :: 4 - Beta
Classifier: Intended Audience :: Developers
Classifier: Topic :: Utilities
Classifier: License :: OSI Approved :: MIT License
Classifier: Programming Language :: Python :: 3
Classifier: Programming Language :: Python :: 3.8
Requires-Python: >=3.8
License-File: LICENSE
